archive_project/__init__.py
archive_project/cli.py
archive_project/main.py
archive_project-1.0.0.dist-info/LICENSE.md
archive_project-1.0.0.dist-info/METADATA
archive_project-1.0.0.dist-info/WHEEL
archive_project-1.0.0.dist-info/entry_points.txt
archive_project-1.0.0.dist-info/top_level.txt
archive_project-1.0.0.dist-info/RECORD
