Metadata-Version: 2.1
Name: archive-project
Version: 1.0.0
Summary: The CLI tool to zip Python project and copy archive to desktop
Home-page: https://github.com/lancelote/archive-project
Author: Pavel Karateev
Author-email: lancelote.du.lac@gmail.com
License: MIT
Platform: UNKNOWN
Classifier: License :: OSI Approved :: MIT License
Classifier: Programming Language :: Python :: 3
Classifier: Programming Language :: Python :: 3 :: Only
Classifier: Programming Language :: Python :: 3.8
Classifier: Programming Language :: Python :: 3.9
Classifier: Programming Language :: Python :: Implementation :: CPython
Requires-Python: >=3.8
License-File: LICENSE.md
Requires-Dist: click
Requires-Dist: importlib-metadata ; python_version < "3.8"
